<annotation verified="no">
  <folder>240pictures</folder>
  <filename>T32L75_W3_A4_R6_P376_g222_7</filename>
  <path>C:/Users/ACER/seadrive_root/Wen-Ting/Shared with me/Wenting/240pictures/T32L75_W3_A4_R6_P376_g222_7.jpg</path>
  <source>
    <database>Unknown</database>
  </source>
  <size>
    <width>2592</width>
    <height>1944</height>
    <depth>3</depth>
  </size>
  <segmented>0</segmented>
  <object>
    <type>robndbox</type>
    <name>blurry.complete</name>
    <pose>Unspecified</pose>
    <truncated>0</truncated>
    <difficult>0</difficult>
    <robndbox>
      <cx>168.0952</cx>
      <cy>286.5195</cy>
      <w>176.6418</w>
      <h>98.5881</h>
      <angle>3.069085</angle>
    </robndbox>
  </object>
  <object>
    <type>robndbox</type>
    <name>blurry.complete</name>
    <pose>Unspecified</pose>
    <truncated>0</truncated>
    <difficult>0</difficult>
    <robndbox>
      <cx>454.2551</cx>
      <cy>287.2857</cy>
      <w>169.0</w>
      <h>96.0</h>
      <angle>0.0</angle>
    </robndbox>
  </object>
  <object>
    <type>robndbox</type>
    <name>blurry.complete</name>
    <pose>Unspecified</pose>
    <truncated>0</truncated>
    <difficult>0</difficult>
    <robndbox>
      <cx>771.2551</cx>
      <cy>293.2857</cy>
      <w>171.0</w>
      <h>92.0</h>
      <angle>0.0</angle>
    </robndbox>
  </object>
  <object>
    <type>robndbox</type>
    <name>blurry.complete</name>
    <pose>Unspecified</pose>
    <truncated>0</truncated>
    <difficult>0</difficult>
    <robndbox>
      <cx>1416.2551</cx>
      <cy>283.2857</cy>
      <w>175.0</w>
      <h>92.0</h>
      <angle>0.0</angle>
    </robndbox>
  </object>
  <object>
    <type>robndbox</type>
    <name>blurry.complete</name>
    <pose>Unspecified</pose>
    <truncated>0</truncated>
    <difficult>0</difficult>
    <robndbox>
      <cx>1716.2551</cx>
      <cy>275.2857</cy>
      <w>159.0</w>
      <h>96.0</h>
      <angle>0.0</angle>
    </robndbox>
  </object>
  <object>
    <type>robndbox</type>
    <name>blurry.complete</name>
    <pose>Unspecified</pose>
    <truncated>0</truncated>
    <difficult>0</difficult>
    <robndbox>
      <cx>1996.7551</cx>
      <cy>270.2857</cy>
      <w>182.0</w>
      <h>94.0</h>
      <angle>3.087232</angle>
    </robndbox>
  </object>
  <object>
    <type>robndbox</type>
    <name>blurry.complete</name>
    <pose>Unspecified</pose>
    <truncated>0</truncated>
    <difficult>0</difficult>
    <robndbox>
      <cx>2315.7551</cx>
      <cy>268.2857</cy>
      <w>194.0</w>
      <h>102.0</h>
      <angle>3.050177</angle>
    </robndbox>
  </object>
  <object>
    <type>robndbox</type>
    <name>blurry.incomplete</name>
    <pose>Unspecified</pose>
    <truncated>0</truncated>
    <difficult>0</difficult>
    <robndbox>
      <cx>75.3776</cx>
      <cy>617.2857</cy>
      <w>150.7551</w>
      <h>106.0</h>
      <angle>0.0</angle>
    </robndbox>
  </object>
  <object>
    <type>robndbox</type>
    <name>blurry.complete</name>
    <pose>Unspecified</pose>
    <truncated>0</truncated>
    <difficult>0</difficult>
    <robndbox>
      <cx>395.7551</cx>
      <cy>614.2857</cy>
      <w>188.0</w>
      <h>100.0</h>
      <angle>0.0</angle>
    </robndbox>
  </object>
  <object>
    <type>robndbox</type>
    <name>complete</name>
    <pose>Unspecified</pose>
    <truncated>0</truncated>
    <difficult>0</difficult>
    <robndbox>
      <cx>521.7551</cx>
      <cy>701.2857</cy>
      <w>194.0</w>
      <h>104.0</h>
      <angle>0.0</angle>
    </robndbox>
  </object>
  <object>
    <type>robndbox</type>
    <name>blurry.complete</name>
    <pose>Unspecified</pose>
    <truncated>0</truncated>
    <difficult>0</difficult>
    <robndbox>
      <cx>840.7551</cx>
      <cy>621.2857</cy>
      <w>188.0</w>
      <h>114.0</h>
      <angle>0.0</angle>
    </robndbox>
  </object>
  <object>
    <type>robndbox</type>
    <name>blurry.complete</name>
    <pose>Unspecified</pose>
    <truncated>0</truncated>
    <difficult>0</difficult>
    <robndbox>
      <cx>1371.7551</cx>
      <cy>600.2857</cy>
      <w>204.0</w>
      <h>118.0</h>
      <angle>0.0</angle>
    </robndbox>
  </object>
  <object>
    <type>robndbox</type>
    <name>complete</name>
    <pose>Unspecified</pose>
    <truncated>0</truncated>
    <difficult>0</difficult>
    <robndbox>
      <cx>1698.7551</cx>
      <cy>678.2857</cy>
      <w>198.0</w>
      <h>106.0</h>
      <angle>0.0</angle>
    </robndbox>
  </object>
  <object>
    <type>robndbox</type>
    <name>complete</name>
    <pose>Unspecified</pose>
    <truncated>0</truncated>
    <difficult>0</difficult>
    <robndbox>
      <cx>1983.7551</cx>
      <cy>596.2857</cy>
      <w>200.0</w>
      <h>110.0</h>
      <angle>0.0</angle>
    </robndbox>
  </object>
  <object>
    <type>robndbox</type>
    <name>complete</name>
    <pose>Unspecified</pose>
    <truncated>0</truncated>
    <difficult>0</difficult>
    <robndbox>
      <cx>2263.5579</cx>
      <cy>673.7112</cy>
      <w>199.6962</w>
      <h>100.862</h>
      <angle>0.031743</angle>
    </robndbox>
  </object>
  <object>
    <type>robndbox</type>
    <name>blurry.incomplete</name>
    <pose>Unspecified</pose>
    <truncated>0</truncated>
    <difficult>0</difficult>
    <robndbox>
      <cx>2562.8776</cx>
      <cy>593.2857</cy>
      <w>56.2449</w>
      <h>112.0</h>
      <angle>0.0</angle>
    </robndbox>
  </object>
  <object>
    <type>robndbox</type>
    <name>blurry.complete</name>
    <pose>Unspecified</pose>
    <truncated>0</truncated>
    <difficult>0</difficult>
    <robndbox>
      <cx>133.7551</cx>
      <cy>1161.7857</cy>
      <w>154.0</w>
      <h>93.0</h>
      <angle>0.0</angle>
    </robndbox>
  </object>
  <object>
    <type>robndbox</type>
    <name>blurry.complete</name>
    <pose>Unspecified</pose>
    <truncated>0</truncated>
    <difficult>0</difficult>
    <robndbox>
      <cx>487.9439</cx>
      <cy>1155.8924</cy>
      <w>200.5304</w>
      <h>99.2924</h>
      <angle>3.109401</angle>
    </robndbox>
  </object>
  <object>
    <type>robndbox</type>
    <name>blurry.complete</name>
    <pose>Unspecified</pose>
    <truncated>0</truncated>
    <difficult>0</difficult>
    <robndbox>
      <cx>984.7551</cx>
      <cy>1156.2857</cy>
      <w>186.0</w>
      <h>92.0</h>
      <angle>0.0</angle>
    </robndbox>
  </object>
  <object>
    <type>robndbox</type>
    <name>blurry.complete</name>
    <pose>Unspecified</pose>
    <truncated>0</truncated>
    <difficult>0</difficult>
    <robndbox>
      <cx>1478.7551</cx>
      <cy>1144.2857</cy>
      <w>202.0</w>
      <h>96.0</h>
      <angle>3.103962</angle>
    </robndbox>
  </object>
  <object>
    <type>robndbox</type>
    <name>blurry.complete</name>
    <pose>Unspecified</pose>
    <truncated>0</truncated>
    <difficult>0</difficult>
    <robndbox>
      <cx>1917.7551</cx>
      <cy>1139.2857</cy>
      <w>194.0</w>
      <h>94.0</h>
      <angle>0.0</angle>
    </robndbox>
  </object>
  <object>
    <type>robndbox</type>
    <name>blurry.complete</name>
    <pose>Unspecified</pose>
    <truncated>0</truncated>
    <difficult>0</difficult>
    <robndbox>
      <cx>2410.2551</cx>
      <cy>1133.2857</cy>
      <w>209.0</w>
      <h>102.0</h>
      <angle>0.0</angle>
    </robndbox>
  </object>
  <object>
    <type>robndbox</type>
    <name>blurry.incomplete</name>
    <pose>Unspecified</pose>
    <truncated>0</truncated>
    <difficult>0</difficult>
    <robndbox>
      <cx>33.8776</cx>
      <cy>1513.9805</cy>
      <w>67.7551</w>
      <h>117.3897</h>
      <angle>0.0</angle>
    </robndbox>
  </object>
  <object>
    <type>robndbox</type>
    <name>blurry.complete</name>
    <pose>Unspecified</pose>
    <truncated>0</truncated>
    <difficult>0</difficult>
    <robndbox>
      <cx>377.1581</cx>
      <cy>1509.0149</cy>
      <w>199.0897</w>
      <h>98.0567</h>
      <angle>3.074758</angle>
    </robndbox>
  </object>
  <object>
    <type>robndbox</type>
    <name>blurry.complete</name>
    <pose>Unspecified</pose>
    <truncated>0</truncated>
    <difficult>0</difficult>
    <robndbox>
      <cx>710.2551</cx>
      <cy>1506.7857</cy>
      <w>187.0</w>
      <h>107.0</h>
      <angle>0.0</angle>
    </robndbox>
  </object>
  <object>
    <type>robndbox</type>
    <name>blurry.complete</name>
    <pose>Unspecified</pose>
    <truncated>0</truncated>
    <difficult>0</difficult>
    <robndbox>
      <cx>1077.7551</cx>
      <cy>1502.2857</cy>
      <w>176.0</w>
      <h>106.0</h>
      <angle>0.0</angle>
    </robndbox>
  </object>
  <object>
    <type>robndbox</type>
    <name>blurry.complete</name>
    <pose>Unspecified</pose>
    <truncated>0</truncated>
    <difficult>0</difficult>
    <robndbox>
      <cx>1392.7551</cx>
      <cy>1515.2857</cy>
      <w>190.0</w>
      <h>98.0</h>
      <angle>0.0</angle>
    </robndbox>
  </object>
  <object>
    <type>robndbox</type>
    <name>blurry.complete</name>
    <pose>Unspecified</pose>
    <truncated>0</truncated>
    <difficult>0</difficult>
    <robndbox>
      <cx>1742.7551</cx>
      <cy>1499.2857</cy>
      <w>184.0</w>
      <h>100.0</h>
      <angle>0.0</angle>
    </robndbox>
  </object>
  <object>
    <type>robndbox</type>
    <name>blurry.complete</name>
    <pose>Unspecified</pose>
    <truncated>0</truncated>
    <difficult>0</difficult>
    <robndbox>
      <cx>2091.7551</cx>
      <cy>1493.2857</cy>
      <w>176.0</w>
      <h>104.0</h>
      <angle>0.0</angle>
    </robndbox>
  </object>
  <object>
    <type>robndbox</type>
    <name>blurry.complete</name>
    <pose>Unspecified</pose>
    <truncated>0</truncated>
    <difficult>0</difficult>
    <robndbox>
      <cx>2422.2551</cx>
      <cy>1488.2857</cy>
      <w>167.0</w>
      <h>98.0</h>
      <angle>0.0</angle>
    </robndbox>
  </object>
  <object>
    <type>robndbox</type>
    <name>hair</name>
    <pose>Unspecified</pose>
    <truncated>0</truncated>
    <difficult>0</difficult>
    <robndbox>
      <cx>770.5225</cx>
      <cy>72.7614</cy>
      <w>63.3979</w>
      <h>134.2508</h>
      <angle>2.480549</angle>
    </robndbox>
  </object>
  <object>
    <type>robndbox</type>
    <name>hair</name>
    <pose>Unspecified</pose>
    <truncated>0</truncated>
    <difficult>0</difficult>
    <robndbox>
      <cx>1381.5441</cx>
      <cy>70.6429</cy>
      <w>57.6404</w>
      <h>113.8882</h>
      <angle>2.480549</angle>
    </robndbox>
  </object>
  <object>
    <type>robndbox</type>
    <name>hair</name>
    <pose>Unspecified</pose>
    <truncated>0</truncated>
    <difficult>0</difficult>
    <robndbox>
      <cx>1095.7551</cx>
      <cy>690.2857</cy>
      <w>94.0</w>
      <h>70.0</h>
      <angle>0.0</angle>
    </robndbox>
  </object>
  <object>
    <type>robndbox</type>
    <name>hair</name>
    <pose>Unspecified</pose>
    <truncated>0</truncated>
    <difficult>0</difficult>
    <robndbox>
      <cx>1196.7963</cx>
      <cy>1607.3011</cy>
      <w>65.0658</w>
      <h>98.4218</h>
      <angle>2.541207</angle>
    </robndbox>
  </object>
</annotation>
