<annotation verified="no">
  <folder>240pictures</folder>
  <filename>T32L75_W3_A4_R6_P331_g108_4</filename>
  <path>C:/Users/ACER/seadrive_root/Wen-Ting/Shared with me/Wenting/240pictures/T32L75_W3_A4_R6_P331_g108_4.jpg</path>
  <source>
    <database>Unknown</database>
  </source>
  <size>
    <width>2592</width>
    <height>1944</height>
    <depth>3</depth>
  </size>
  <segmented>0</segmented>
  <object>
    <type>robndbox</type>
    <name>blurry.complete</name>
    <pose>Unspecified</pose>
    <truncated>0</truncated>
    <difficult>0</difficult>
    <robndbox>
      <cx>215.878</cx>
      <cy>194.5655</cy>
      <w>204.1726</w>
      <h>105.2976</h>
      <angle>0.0</angle>
    </robndbox>
  </object>
  <object>
    <type>robndbox</type>
    <name>blurry.complete</name>
    <pose>Unspecified</pose>
    <truncated>0</truncated>
    <difficult>0</difficult>
    <robndbox>
      <cx>659.1527</cx>
      <cy>201.0268</cy>
      <w>186.4487</w>
      <h>106.3272</h>
      <angle>0.043722</angle>
    </robndbox>
  </object>
  <object>
    <type>robndbox</type>
    <name>blurry.complete</name>
    <pose>Unspecified</pose>
    <truncated>0</truncated>
    <difficult>0</difficult>
    <robndbox>
      <cx>917.9788</cx>
      <cy>190.8833</cy>
      <w>176.337</w>
      <h>98.0063</h>
      <angle>0.003722</angle>
    </robndbox>
  </object>
  <object>
    <type>robndbox</type>
    <name>blurry.complete</name>
    <pose>Unspecified</pose>
    <truncated>0</truncated>
    <difficult>0</difficult>
    <robndbox>
      <cx>1261.3925</cx>
      <cy>185.8595</cy>
      <w>197.1715</w>
      <h>99.8812</h>
      <angle>0.003722</angle>
    </robndbox>
  </object>
  <object>
    <type>robndbox</type>
    <name>blurry.complete</name>
    <pose>Unspecified</pose>
    <truncated>0</truncated>
    <difficult>0</difficult>
    <robndbox>
      <cx>2050.9322</cx>
      <cy>197.6481</cy>
      <w>200.7543</w>
      <h>115.3276</h>
      <angle>0.039332</angle>
    </robndbox>
  </object>
  <object>
    <type>robndbox</type>
    <name>blurry.complete</name>
    <pose>Unspecified</pose>
    <truncated>0</truncated>
    <difficult>0</difficult>
    <robndbox>
      <cx>1586.9788</cx>
      <cy>190.3833</cy>
      <w>202.3628</w>
      <h>104.9095</h>
      <angle>0.003722</angle>
    </robndbox>
  </object>
  <object>
    <type>robndbox</type>
    <name>blurry.incomplete</name>
    <pose>Unspecified</pose>
    <truncated>0</truncated>
    <difficult>0</difficult>
    <robndbox>
      <cx>2523.3958</cx>
      <cy>201.2802</cy>
      <w>134.6884</w>
      <h>108.422</h>
      <angle>0.004809</angle>
    </robndbox>
  </object>
  <object>
    <type>robndbox</type>
    <name>blurry.incomplete</name>
    <pose>Unspecified</pose>
    <truncated>0</truncated>
    <difficult>0</difficult>
    <robndbox>
      <cx>113.8596</cx>
      <cy>658.0</cy>
      <w>227.7193</w>
      <h>88.0</h>
      <angle>0.0</angle>
    </robndbox>
  </object>
  <object>
    <type>robndbox</type>
    <name>blurry.complete</name>
    <pose>Unspecified</pose>
    <truncated>0</truncated>
    <difficult>0</difficult>
    <robndbox>
      <cx>585.4288</cx>
      <cy>648.9852</cy>
      <w>205.6801</w>
      <h>87.3549</h>
      <angle>3.091541</angle>
    </robndbox>
  </object>
  <object>
    <type>robndbox</type>
    <name>blurry.complete</name>
    <pose>Unspecified</pose>
    <truncated>0</truncated>
    <difficult>0</difficult>
    <robndbox>
      <cx>1057.097</cx>
      <cy>640.2366</cy>
      <w>195.0581</w>
      <h>85.3965</h>
      <angle>3.11338</angle>
    </robndbox>
  </object>
  <object>
    <type>robndbox</type>
    <name>blurry.complete</name>
    <pose>Unspecified</pose>
    <truncated>0</truncated>
    <difficult>0</difficult>
    <robndbox>
      <cx>1352.9849</cx>
      <cy>642.5437</cy>
      <w>181.0511</w>
      <h>95.7071</h>
      <angle>0.031384</angle>
    </robndbox>
  </object>
  <object>
    <type>robndbox</type>
    <name>blurry.complete</name>
    <pose>Unspecified</pose>
    <truncated>0</truncated>
    <difficult>0</difficult>
    <robndbox>
      <cx>1878.0161</cx>
      <cy>648.1329</cy>
      <w>192.6941</w>
      <h>100.9016</h>
      <angle>0.014161</angle>
    </robndbox>
  </object>
  <object>
    <type>robndbox</type>
    <name>blurry.complete</name>
    <pose>Unspecified</pose>
    <truncated>0</truncated>
    <difficult>0</difficult>
    <robndbox>
      <cx>2289.0072</cx>
      <cy>660.2648</cy>
      <w>184.7938</w>
      <h>85.1956</h>
      <angle>0.014161</angle>
    </robndbox>
  </object>
  <object>
    <type>robndbox</type>
    <name>blurry.complete</name>
    <pose>Unspecified</pose>
    <truncated>0</truncated>
    <difficult>0</difficult>
    <robndbox>
      <cx>271.76</cx>
      <cy>968.3916</cy>
      <w>191.5891</w>
      <h>99.5301</h>
      <angle>3.090651</angle>
    </robndbox>
  </object>
  <object>
    <type>robndbox</type>
    <name>blurry.complete</name>
    <pose>Unspecified</pose>
    <truncated>0</truncated>
    <difficult>0</difficult>
    <robndbox>
      <cx>743.1477</cx>
      <cy>959.3762</cy>
      <w>181.0394</w>
      <h>96.7949</h>
      <angle>3.135423</angle>
    </robndbox>
  </object>
  <object>
    <type>robndbox</type>
    <name>blurry.complete</name>
    <pose>Unspecified</pose>
    <truncated>0</truncated>
    <difficult>0</difficult>
    <robndbox>
      <cx>1136.5614</cx>
      <cy>948.8524</cy>
      <w>177.8857</w>
      <h>93.7278</h>
      <angle>3.135423</angle>
    </robndbox>
  </object>
  <object>
    <type>robndbox</type>
    <name>blurry.complete</name>
    <pose>Unspecified</pose>
    <truncated>0</truncated>
    <difficult>0</difficult>
    <robndbox>
      <cx>1830.1475</cx>
      <cy>967.8394</cy>
      <w>176.8737</w>
      <h>81.66</h>
      <angle>3.135423</angle>
    </robndbox>
  </object>
  <object>
    <type>robndbox</type>
    <name>blurry.complete</name>
    <pose>Unspecified</pose>
    <truncated>0</truncated>
    <difficult>0</difficult>
    <robndbox>
      <cx>2410.0252</cx>
      <cy>970.2691</cy>
      <w>168.7837</w>
      <h>98.505</h>
      <angle>3.135423</angle>
    </robndbox>
  </object>
  <object>
    <type>robndbox</type>
    <name>blurry.complete</name>
    <pose>Unspecified</pose>
    <truncated>0</truncated>
    <difficult>0</difficult>
    <robndbox>
      <cx>575.5252</cx>
      <cy>1418.7691</cy>
      <w>163.7282</w>
      <h>107.474</h>
      <angle>3.135423</angle>
    </robndbox>
  </object>
  <object>
    <type>robndbox</type>
    <name>blurry.complete</name>
    <pose>Unspecified</pose>
    <truncated>0</truncated>
    <difficult>0</difficult>
    <robndbox>
      <cx>165.5252</cx>
      <cy>1411.2691</cy>
      <w>175.8082</w>
      <h>94.5483</h>
      <angle>3.104808</angle>
    </robndbox>
  </object>
  <object>
    <type>robndbox</type>
    <name>blurry.complete</name>
    <pose>Unspecified</pose>
    <truncated>0</truncated>
    <difficult>0</difficult>
    <robndbox>
      <cx>840.6534</cx>
      <cy>1402.9348</cy>
      <w>174.8065</w>
      <h>94.0347</h>
      <angle>3.030799</angle>
    </robndbox>
  </object>
  <object>
    <type>robndbox</type>
    <name>blurry.complete</name>
    <pose>Unspecified</pose>
    <truncated>0</truncated>
    <difficult>0</difficult>
    <robndbox>
      <cx>1473.619</cx>
      <cy>1425.3268</cy>
      <w>203.0096</w>
      <h>94.9674</h>
      <angle>0.023816</angle>
    </robndbox>
  </object>
  <object>
    <type>robndbox</type>
    <name>blurry.complete</name>
    <pose>Unspecified</pose>
    <truncated>0</truncated>
    <difficult>0</difficult>
    <robndbox>
      <cx>2052.515</cx>
      <cy>1424.2115</cy>
      <w>186.7338</w>
      <h>96.7188</h>
      <angle>0.003816</angle>
    </robndbox>
  </object>
  <object>
    <type>robndbox</type>
    <name>blurry.incomplete</name>
    <pose>Unspecified</pose>
    <truncated>0</truncated>
    <difficult>0</difficult>
    <robndbox>
      <cx>2546.5328</cx>
      <cy>1441.835</cy>
      <w>88.2743</w>
      <h>101.5487</h>
      <angle>0.013816</angle>
    </robndbox>
  </object>
  <object>
    <type>robndbox</type>
    <name>blurry.complete</name>
    <pose>Unspecified</pose>
    <truncated>0</truncated>
    <difficult>0</difficult>
    <robndbox>
      <cx>264.4103</cx>
      <cy>1725.2279</cy>
      <w>170.0324</w>
      <h>101.2049</h>
      <angle>0.013816</angle>
    </robndbox>
  </object>
  <object>
    <type>robndbox</type>
    <name>blurry.complete</name>
    <pose>Unspecified</pose>
    <truncated>0</truncated>
    <difficult>0</difficult>
    <robndbox>
      <cx>561.5328</cx>
      <cy>1733.835</cy>
      <w>168.0457</w>
      <h>84.445</h>
      <angle>0.013816</angle>
    </robndbox>
  </object>
  <object>
    <type>robndbox</type>
    <name>blurry.complete</name>
    <pose>Unspecified</pose>
    <truncated>0</truncated>
    <difficult>0</difficult>
    <robndbox>
      <cx>922.4103</cx>
      <cy>1728.7279</cy>
      <w>175.8523</w>
      <h>88.1232</h>
      <angle>0.013816</angle>
    </robndbox>
  </object>
  <object>
    <type>robndbox</type>
    <name>blurry.complete</name>
    <pose>Unspecified</pose>
    <truncated>0</truncated>
    <difficult>0</difficult>
    <robndbox>
      <cx>1409.9942</cx>
      <cy>1732.9665</cy>
      <w>181.1009</w>
      <h>90.4243</h>
      <angle>0.033816</angle>
    </robndbox>
  </object>
  <object>
    <type>robndbox</type>
    <name>blurry.complete</name>
    <pose>Unspecified</pose>
    <truncated>0</truncated>
    <difficult>0</difficult>
    <robndbox>
      <cx>1911.3694</cx>
      <cy>1734.6472</cy>
      <w>191.6996</w>
      <h>92.2956</h>
      <angle>3.095166</angle>
    </robndbox>
  </object>
  <object>
    <type>robndbox</type>
    <name>blurry.complete</name>
    <pose>Unspecified</pose>
    <truncated>0</truncated>
    <difficult>0</difficult>
    <robndbox>
      <cx>2436.3678</cx>
      <cy>1734.6276</cy>
      <w>192.2121</w>
      <h>97.4334</h>
      <angle>0.030097</angle>
    </robndbox>
  </object>
  <object>
    <type>robndbox</type>
    <name>hair</name>
    <pose>Unspecified</pose>
    <truncated>0</truncated>
    <difficult>0</difficult>
    <robndbox>
      <cx>372.2193</cx>
      <cy>1554.5</cy>
      <w>209.0</w>
      <h>73.0</h>
      <angle>0.312469</angle>
    </robndbox>
  </object>
  <object>
    <type>robndbox</type>
    <name>hair</name>
    <pose>Unspecified</pose>
    <truncated>0</truncated>
    <difficult>0</difficult>
    <robndbox>
      <cx>1164.4656</cx>
      <cy>1550.0353</cy>
      <w>155.2718</w>
      <h>58.607</h>
      <angle>0.285232</angle>
    </robndbox>
  </object>
  <object>
    <type>robndbox</type>
    <name>hair</name>
    <pose>Unspecified</pose>
    <truncated>0</truncated>
    <difficult>0</difficult>
    <robndbox>
      <cx>2113.7279</cx>
      <cy>1571.4533</cy>
      <w>211.6784</w>
      <h>65.6621</h>
      <angle>0.43709</angle>
    </robndbox>
  </object>
  <object>
    <type>robndbox</type>
    <name>hair</name>
    <pose>Unspecified</pose>
    <truncated>0</truncated>
    <difficult>0</difficult>
    <robndbox>
      <cx>1418.4331</cx>
      <cy>1040.0641</cy>
      <w>133.1218</w>
      <h>68.0597</h>
      <angle>0.63671</angle>
    </robndbox>
  </object>
  <object>
    <type>robndbox</type>
    <name>hair</name>
    <pose>Unspecified</pose>
    <truncated>0</truncated>
    <difficult>0</difficult>
    <robndbox>
      <cx>735.2957</cx>
      <cy>528.5717</cy>
      <w>125.6812</w>
      <h>65.0831</h>
      <angle>1.05186</angle>
    </robndbox>
  </object>
  <object>
    <type>robndbox</type>
    <name>hair</name>
    <pose>Unspecified</pose>
    <truncated>0</truncated>
    <difficult>0</difficult>
    <robndbox>
      <cx>2266.7957</cx>
      <cy>881.5717</cy>
      <w>140.8087</w>
      <h>87.5366</h>
      <angle>1.05186</angle>
    </robndbox>
  </object>
  <object>
    <type>robndbox</type>
    <name>hair</name>
    <pose>Unspecified</pose>
    <truncated>0</truncated>
    <difficult>0</difficult>
    <robndbox>
      <cx>1869.2006</cx>
      <cy>868.426</cy>
      <w>190.5833</w>
      <h>97.212</h>
      <angle>0.63671</angle>
    </robndbox>
  </object>
  <object>
    <type>robndbox</type>
    <name>hair</name>
    <pose>Unspecified</pose>
    <truncated>0</truncated>
    <difficult>0</difficult>
    <robndbox>
      <cx>1203.2381</cx>
      <cy>341.9048</cy>
      <w>102.0</w>
      <h>150.0</h>
      <angle>0.188222</angle>
    </robndbox>
  </object>
</annotation>
